LICENCE.txt
README.md
setup.py
fpcmci/CPrinter.py
fpcmci/FPCMCI.py
fpcmci/PCMCI.py
fpcmci/__init__.py
fpcmci/version.py
fpcmci.egg-info/PKG-INFO
fpcmci.egg-info/SOURCES.txt
fpcmci.egg-info/dependency_links.txt
fpcmci.egg-info/requires.txt
fpcmci.egg-info/top_level.txt
fpcmci/basics/__init__.py
fpcmci/basics/constants.py
fpcmci/basics/logger.py
fpcmci/basics/utils.py
fpcmci/graph/DAG.py
fpcmci/graph/Node.py
fpcmci/graph/__init__.py
fpcmci/preprocessing/Subsampler.py
fpcmci/preprocessing/__init__.py
fpcmci/preprocessing/data.py
fpcmci/preprocessing/subsampling_methods/EntropyBasedMethod.py
fpcmci/preprocessing/subsampling_methods/Static.py
fpcmci/preprocessing/subsampling_methods/SubsamplingMethod.py
fpcmci/preprocessing/subsampling_methods/WSDynamic.py
fpcmci/preprocessing/subsampling_methods/WSFFTStatic.py
fpcmci/preprocessing/subsampling_methods/WSStatic.py
fpcmci/preprocessing/subsampling_methods/__init__.py
fpcmci/preprocessing/subsampling_methods/moving_window.py
fpcmci/selection_methods/Corr.py
fpcmci/selection_methods/MI.py
fpcmci/selection_methods/ParCorr.py
fpcmci/selection_methods/SelectionMethod.py
fpcmci/selection_methods/TE.py
fpcmci/selection_methods/__init__.py