Metadata-Version: 2.1
Name: fpcmci
Version: 4.4.1
Summary: A causal discovery Python package
Home-page: https://github.com/lcastri/fpcmci
Author: Luca Castri
Author-email: lucacastri94@gmail.com
Classifier: Development Status :: 4 - Beta
Classifier: Intended Audience :: Science/Research
Classifier: License :: OSI Approved :: GNU General Public License v3 (GPLv3)
Classifier: Programming Language :: Python :: 3
Classifier: Topic :: Scientific/Engineering :: Artificial Intelligence
Requires-Python: >=3
License-File: LICENCE.txt
Requires-Dist: tigramite>=5.1.0.3
Requires-Dist: pandas>=1.5.2
Requires-Dist: netgraph>=4.10.2
Requires-Dist: networkx>=2.8.6
Requires-Dist: ruptures>=1.1.7
Requires-Dist: scikit_learn>=1.1.3
Requires-Dist: torch>=1.11.0
Requires-Dist: gpytorch>=1.4
Requires-Dist: dcor>=0.5.3
Requires-Dist: h5py>=3.7.0
Requires-Dist: jpype1>=1.5.0
Requires-Dist: mpmath>=1.3.0
